togu
