Metadata-Version: 1.1
Name: togu
Version: 0.1.1
Summary: supervisord event listener to watch shinken daemons
Home-page: https://github.com/nlm/togu
Author: Nicolas Limage
Author-email: UNKNOWN
License: MIT
Keywords: shinken watch supervisord
Platform: UNKNOWN
Classifier: Development Status :: 4 - Beta
Classifier: Environment :: Console
Classifier: Intended Audience :: System Administrators
Classifier: License :: OSI Approved :: GNU General Public License (GPL)
Classifier: Operating System :: OS Independent
Classifier: Programming Language :: Python
Classifier: Topic :: System :: Monitoring
